MANIFEST.in
README.rst
TITLE.txt
lh-agpl3-LICENSE.txt
setup.py
bin/bx-platformInfoManage.py
bisos2/__init__.py
bisos2.platform.egg-info/PKG-INFO
bisos2.platform.egg-info/SOURCES.txt
bisos2.platform.egg-info/dependency_links.txt
bisos2.platform.egg-info/namespace_packages.txt
bisos2.platform.egg-info/not-zip-safe
bisos2.platform.egg-info/requires.txt
bisos2.platform.egg-info/top_level.txt
bisos2/platform/__init__.py
bisos2/platform/bxPlatformConfig.py
bisos2/platform/bxPlatformThis.py